croudtech_python_aws_app_config/__init__.py
croudtech_python_aws_app_config/cli.py
croudtech_python_aws_app_config/metrics.py
croudtech_python_aws_app_config/redis_config.py
croudtech_python_aws_app_config/response.py
croudtech_python_aws_app_config/ssm_config.py
croudtech_python_aws_app_config/tests/__init__.py
croudtech_python_aws_app_config/tests/conftest.py
croudtech_python_aws_app_config/tests/redis_config_test.py
croudtech_python_aws_app_config-2.0.2.dist-info/AUTHORS.rst
croudtech_python_aws_app_config-2.0.2.dist-info/LICENSE.txt
croudtech_python_aws_app_config-2.0.2.dist-info/METADATA
croudtech_python_aws_app_config-2.0.2.dist-info/WHEEL
croudtech_python_aws_app_config-2.0.2.dist-info/RECORD
