Metadata-Version: 2.1
Name: croudtech-python-aws-app-config
Version: 2.0.2
Summary: 
Author: Jim Robinson
Author-email: jim.robinson@croud.com
Requires-Python: >=3.12,<4.0
Classifier: Programming Language :: Python :: 3
Classifier: Programming Language :: Python :: 3.12
Requires-Dist: PyYAML (>=6.0.1,<7.0.0)
Requires-Dist: boto3 (>=1.34.105,<2.0.0)
Requires-Dist: bson (>=0.5.10,<0.6.0)
Requires-Dist: click (>=8.1.7,<9.0.0)
Requires-Dist: http-status-codes (>=1.0.3,<2.0.0)
Requires-Dist: loguru (>=0.7.2,<0.8.0)
Requires-Dist: pyaml (>=24.4.0,<25.0.0)
Requires-Dist: redis (>=5.0.4,<6.0.0)
Requires-Dist: requests (>=2.31.0,<3.0.0)
